MANIFEST.in
Readme.rst
requirements.txt
setup.py
Agile_Diamond.egg-info/PKG-INFO
Agile_Diamond.egg-info/SOURCES.txt
Agile_Diamond.egg-info/dependency_links.txt
Agile_Diamond.egg-info/not-zip-safe
Agile_Diamond.egg-info/requires.txt
Agile_Diamond.egg-info/top_level.txt
agile_diamond/__init__.py
agile_diamond/__meta__.py
bin/agile-new.sh
skels/agile-software/.gitignore
skels/agile-software/.mrbob.ini
skels/agile-software/Makefile.bob
skels/agile-software/Readme.md
skels/agile-software/assets/.DS_Store
skels/agile-software/assets/docx/reference.docx
skels/agile-software/assets/script/amalgamate.pl
skels/agile-software/assets/script/omnigraffle-export.applescript
skels/agile-software/assets/script/omnioutliner-export.applescript
skels/agile-software/assets/script/omniplan-export.applescript
skels/agile-software/assets/www/index.html.bob
skels/agile-software/assets/www/ryangray-style.css
skels/agile-software/assets/www/style.css
skels/agile-software/assets/www/template.html.bob
skels/agile-software/assets/www/unimplemented.html
skels/agile-software/docs/+project_name+_Project_Guide.md.bob
skels/agile-software/docs/compliance/+project_name+_Compliance_Header.md.bob
skels/agile-software/docs/compliance/+project_name+_Hazards_Register.md.bob
skels/agile-software/docs/compliance/+project_name+_Mitigations_Register.md.bob
skels/agile-software/docs/compliance/+project_name+_Requirements.md.bob
skels/agile-software/docs/compliance/+project_name+_Risks_Register.md.bob
skels/agile-software/docs/compliance/+project_name+_Security.md.bob
skels/agile-software/docs/compliance/+project_name+_Tests_Register.md.bob
skels/agile-software/docs/design/+project_name+_Design.md.bob
skels/agile-software/docs/design/.DS_Store
skels/agile-software/docs/design/+project_name+_Entity_Relationship_Diagram.graffle/data.plist
skels/agile-software/docs/design/+project_name+_Flowcharts.graffle/data.plist
skels/agile-software/docs/design/+project_name+_Process_Map.graffle/data.plist
skels/agile-software/docs/design/+project_name+_Site_Map.graffle/data.plist
skels/agile-software/docs/design/+project_name+_System_Map.graffle/data.plist
skels/agile-software/docs/design/+project_name+_Wireframes.graffle/data.plist
